[
 {
  "letter_num":1,
  "from":"Zainab Ibrahim",
  "to":"Fatima, Ibrahim",
  "date":"8\/3\/17**",
  "location":"Kano",
  "notes":null
 },
 {
  "letter_num":2,
  "from":"Nura Abdullahi",
  "to":"Maryam Ibrahim",
  "date":"8\/4\/17**",
  "location":"Borno",
  "notes":null
 },
 {
  "letter_num":3,
  "from":"Sani Abdullahi",
  "to":"Nura Abdullahi",
  "date":"8\/4\/17**",
  "location":"Katsina",
  "notes":null
 },
 {
  "letter_num":4,
  "from":"Fatima, Ibrahim",
  "to":"Zainab Ibrahim",
  "date":"8\/5\/17**",
  "location":"Abuja",
  "notes":null
 },
 {
  "letter_num":5,
  "from":"Amina Ibrahim",
  "to":"Rukayya Ibrahim",
  "date":"8\/7\/17**",
  "location":"Adamawa",
  "notes":null
 },
 {
  "letter_num":6,
  "from":"Jamila Ibrahim",
  "to":"Zainab Ibrahim",
  "date":"8\/9\/17**",
  "location":"USA",
  "notes":null
 },
 {
  "letter_num":7,
  "from":"Maryam Ibrahim",
  "to":"Mahmud Musa",
  "date":"8\/7\/17**",
  "location":"Yobe",
  "notes":null
 },
 {
  "letter_num":8,
  "from":"Yusif Kabir",
  "to":"Yusif Kabir",
  "date":"8\/9\/17**",
  "location":"Saudia",
  "notes":null
 },
 {
  "letter_num":9,
  "from":"Ibrahim Isah",
  "to":"Umar Siraj",
  "date":"8\/11\/17**",
  "location":"China",
  "notes":null
 },
 {
  "letter_num":10,
  "from":"Umar Siraj",
  "to":"Maryam Ibrahim",
  "date":"8\/12\/17**",
  "location":"Sokoto",
  "notes":null
 },
 {
  "letter_num":11,
  "from":"Aisha Sani",
  "to":"Jamila Ibrahim",
  "date":"8\/13\/17**",
  "location":"Taraba",
  "notes":null
 },
 {
  "letter_num":12,
  "from":"Usman",
  "to":"Nura Abdullahi",
  "date":"8\/13\/17**",
  "location":"Kebbi",
  "notes":null
 },
 {
  "letter_num":13,
  "from":"Mahmud Musa",
  "to":"Amina Ibrahim",
  "date":"8\/13\/17**",
  "location":"Lagos",
  "notes":null
 },
 {
  "letter_num":14,
  "from":"Muhammad Ibrahim",
  "to":"Aisha Sani",
  "date":"8\/14\/17**",
  "location":"China",
  "notes":null
 },
 {
  "letter_num":15,
  "from":"Rukayya Ibrahim",
  "to":"Usman",
  "date":"8\/15\/17**",
  "location":"Sokoto",
  "notes":null
 },
 {
  "letter_num":16,
  "from":"Fatima, Ibrahim",
  "to":"Ibrahim Isah",
  "date":"8\/19\/17**",
  "location":"Saudia",
  "notes":null
 },
 {
  "letter_num":17,
  "from":"Yusif Kabir",
  "to":"Fatima, Ibrahim",
  "date":"8\/18\/17**",
  "location":"Katsina",
  "notes":null
 },
 {
  "letter_num":18,
  "from":"Amina Ibrahim",
  "to":"Muhammad Ibrahim ",
  "date":"8\/20\/17**",
  "location":"Lagos",
  "notes":null
 },
 {
  "letter_num":19,
  "from":"Maryam Ibrahim",
  "to":"Sani Abdullahi",
  "date":"8\/20\/17**",
  "location":"Abuja",
  "notes":null
 },
 {
  "letter_num":20,
  "from":"Ibrahim Isah",
  "to":"Maryam Ibrahim",
  "date":"8\/20\/17**",
  "location":"Borno",
  "notes":null
 },
 {
  "letter_num":21,
  "from":"Usman",
  "to":"Usman",
  "date":"8\/20\/17**",
  "location":"Taraba",
  "notes":null
 },
 {
  "letter_num":22,
  "from":"Mahmud Musa",
  "to":"Zainab Ibrahim",
  "date":"8\/20\/17**",
  "location":"Kano",
  "notes":null
 },
 {
  "letter_num":23,
  "from":"Zainab Ibrahim",
  "to":"Nura Abdullahi",
  "date":"8\/21\/17**",
  "location":"USA",
  "notes":"4h am"
 },
 {
  "letter_num":24,
  "from":"Nura Abdullahi",
  "to":"Mahmud Musa",
  "date":"8\/20\/17**",
  "location":"Yobe",
  "notes":null
 },
 {
  "letter_num":25,
  "from":"Umar Siraj",
  "to":"Yusif Kabir",
  "date":"8\/22\/17**",
  "location":"Kebbi",
  "notes":null
 },
 {
  "letter_num":26,
  "from":"Muhammad Ibrahim ",
  "to":"Amina Ibrahim",
  "date":"8\/21\/17**",
  "location":"Adamawa",
  "notes":null
 },
 {
  "letter_num":27,
  "from":"Jamila Ibrahim",
  "to":"Jamila Ibrahim",
  "date":"8\/23\/17**",
  "location":"Yobe",
  "notes":null
 },
 {
  "letter_num":28,
  "from":"Sani Abdullahi",
  "to":"Sani Abdullahi",
  "date":"8\/23\/17**",
  "location":"China",
  "notes":null
 },
 {
  "letter_num":29,
  "from":"Rukayya Ibrahim",
  "to":"Umar Siraj",
  "date":"8\/24\/17**",
  "location":"USA",
  "notes":null
 },
 {
  "letter_num":30,
  "from":"Aisha Sani",
  "to":"Rukayya Ibrahim",
  "date":"8\/24\/17**",
  "location":"Adamawa",
  "notes":null
 },
 {
  "letter_num":31,
  "from":"Yusif Kabir",
  "to":"Fatima, Ibrahim",
  "date":"8\/25\/17**",
  "location":"Lagos",
  "notes":null
 },
 {
  "letter_num":32,
  "from":"Fatima, Ibrahim",
  "to":"Ibrahim Isah",
  "date":"8\/24\/17**",
  "location":"Kebbi",
  "notes":null
 },
 {
  "letter_num":33,
  "from":"Amina Ibrahim",
  "to":"Muhammad Ibrahim ",
  "date":"8\/24\/17**",
  "location":"Sokoto",
  "notes":null
 },
 {
  "letter_num":34,
  "from":"Aisha Sani",
  "to":"Aisha Sani",
  "date":"8\/25\/17**",
  "location":"Saudia",
  "notes":null
 },
 {
  "letter_num":35,
  "from":"Rukayya Ibrahim",
  "to":"Muhammad Ibrahim ",
  "date":"8\/21\/17**",
  "location":"Taraba",
  "notes":null
 },
 {
  "letter_num":36,
  "from":"Jamila Ibrahim",
  "to":"Jamila Ibrahim",
  "date":"8\/23\/17**",
  "location":"Abuja",
  "notes":null
 },
 {
  "letter_num":37,
  "from":"Usman",
  "to":"Amina Ibrahim",
  "date":"8\/25\/17**",
  "location":"Borno",
  "notes":null
 },
 {
  "letter_num":38,
  "from":"Mahmud Musa",
  "to":"Sani Abdullahi",
  "date":"8\/27\/17**",
  "location":"Katsina",
  "notes":null
 },
 {
  "letter_num":39,
  "from":"Umar Siraj",
  "to":"Umar Siraj",
  "date":"8\/27\/17**",
  "location":"Kano",
  "notes":null
 },
 {
  "letter_num":40,
  "from":"Ibrahim Isah",
  "to":"Zainab Ibrahim",
  "date":"none",
  "location":"Sokoto",
  "notes":null
 },
 {
  "letter_num":41,
  "from":"Muhammad Ibrahim ",
  "to":"Yusif Kabir",
  "date":"8\/26\/17**",
  "location":"Borno",
  "notes":null
 },
 {
  "letter_num":42,
  "from":"Sani Abdullahi",
  "to":"Mahmud Musa",
  "date":"8\/26\/17**",
  "location":"Saudia",
  "notes":null
 },
 {
  "letter_num":"40-suite",
  "from":"Maryam Ibrahim",
  "to":"Ibrahim Isah",
  "date":"8\/27\/17**",
  "location":"Adamawa",
  "notes":null
 },
 {
  "letter_num":43,
  "from":"Nura Abdullahi",
  "to":"Nura Abdullahi",
  "date":"8\/27\/17**",
  "location":"Kano",
  "notes":null
 },
 {
  "letter_num":44,
  "from":"Zainab Ibrahim",
  "to":"Fatima, Ibrahim",
  "date":"8\/28\/17**",
  "location":"Abuja",
  "notes":null
 },
 {
  "letter_num":45,
  "from":"Amina Ibrahim",
  "to":"Rukayya Ibrahim",
  "date":"8\/29\/17**",
  "location":"USA",
  "notes":null
 },
 {
  "letter_num":46,
  "from":"Fatima, Ibrahim",
  "to":"Maryam Ibrahim",
  "date":"8\/29\/17**",
  "location":"Lagos",
  "notes":null
 },
 {
  "letter_num":47,
  "from":"Umar Siraj",
  "to":"Aisha Sani",
  "date":"8\/30\/17**",
  "location":"Kebbi",
  "notes":null
 },
 {
  "letter_num":48,
  "from":"Yusif Kabir",
  "to":"Usman",
  "date":"8\/30\/17**",
  "location":"Yobe",
  "notes":null
 },
 {
  "letter_num":49,
  "from":"Nura Abdullahi",
  "to":"Yusif Kabir",
  "date":"8\/31\/17**",
  "location":"China",
  "notes":null
 },
 {
  "letter_num":50,
  "from":"Usman",
  "to":"Maryam Ibrahim",
  "date":"9\/1\/17**",
  "location":"Taraba",
  "notes":null
 },
 {
  "letter_num":51,
  "from":"Ibrahim Isah",
  "to":"Aisha Sani",
  "date":"9\/2\/17**",
  "location":"Katsina",
  "notes":null
 },
 {
  "letter_num":52,
  "from":"Muhammad Ibrahim ",
  "to":"Mahmud Musa",
  "date":"9\/3\/17**",
  "location":"Sokoto",
  "notes":null
 },
 {
  "letter_num":53,
  "from":"Sani Abdullahi",
  "to":"Sani Abdullahi",
  "date":"9\/3\/17**",
  "location":"Kebbi",
  "notes":null
 },
 {
  "letter_num":54,
  "from":"Aisha Sani",
  "to":"Muhammad Ibrahim ",
  "date":"9\/4\/17**",
  "location":"Abuja",
  "notes":null
 },
 {
  "letter_num":55,
  "from":"Jamila Ibrahim",
  "to":"Umar Siraj",
  "date":"9\/4\/17**",
  "location":"Taraba",
  "notes":null
 },
 {
  "letter_num":56,
  "from":"Rukayya Ibrahim",
  "to":"Amina Ibrahim",
  "date":"9\/5\/17**",
  "location":"China",
  "notes":null
 },
 {
  "letter_num":57,
  "from":"Maryam Ibrahim",
  "to":"Ibrahim Isah",
  "date":"9\/5\/17**",
  "location":"Yobe",
  "notes":null
 },
 {
  "letter_num":58,
  "from":"Mahmud Musa",
  "to":"Jamila Ibrahim",
  "date":"9\/7\/17**",
  "location":"Saudia",
  "notes":null
 },
 {
  "letter_num":59,
  "from":"Zainab Ibrahim",
  "to":"Zainab Ibrahim",
  "date":"9\/8\/17**",
  "location":"USA",
  "notes":null
 },
 {
  "letter_num":60,
  "from":"Maryam Ibrahim",
  "to":"Rukayya Ibrahim",
  "date":"9\/8\/17**",
  "location":"Adamawa",
  "notes":null
 },
 {
  "letter_num":61,
  "from":"Mahmud Musa",
  "to":"Nura Abdullahi",
  "date":"9\/7\/17**",
  "location":"Katsina",
  "notes":null
 },
 {
  "letter_num":62,
  "from":"Sani Abdullahi",
  "to":"Fatima, Ibrahim",
  "date":"9\/7\/17**",
  "location":"Lagos",
  "notes":null
 },
 {
  "letter_num":63,
  "from":"Ibrahim Isah",
  "to":"Usman",
  "date":"9\/9\/17**",
  "location":"Kano",
  "notes":null
 },
 {
  "letter_num":64,
  "from":"Aisha Sani",
  "to":"Mahmud Musa",
  "date":"9\/9\/17**",
  "location":"Borno",
  "notes":null
 },
 {
  "letter_num":65,
  "from":"Jamila Ibrahim",
  "to":"Maryam Ibrahim",
  "date":"9\/9\/17**",
  "location":"Sokoto",
  "notes":"letter sent, opened, to Merteuil via Valmont in next letter"
 },
 {
  "letter_num":66,
  "from":"Umar Siraj",
  "to":"Zainab Ibrahim",
  "date":"9\/9\/17**",
  "location":"USA",
  "notes":null
 },
 {
  "letter_num":67,
  "from":"Fatima, Ibrahim",
  "to":"Yusif Kabir",
  "date":"9\/9\/17**",
  "location":"Lagos",
  "notes":null
 },
 {
  "letter_num":68,
  "from":"Muhammad Ibrahim ",
  "to":"Nura Abdullahi",
  "date":"9\/10\/17**",
  "location":"Adamawa",
  "notes":null
 },
 {
  "letter_num":69,
  "from":"Yusif Kabir",
  "to":"Aisha Sani",
  "date":"9\/10\/17**",
  "location":"Yobe",
  "notes":"letter oopied by Danceny"
 },
 {
  "letter_num":70,
  "from":"Rukayya Ibrahim",
  "to":"Sani Abdullahi",
  "date":"9\/11\/17**",
  "location":"China",
  "notes":null
 },
 {
  "letter_num":71,
  "from":"Nura Abdullahi",
  "to":"Ibrahim Isah",
  "date":"9\/13\/17**",
  "location":"Kebbi",
  "notes":null
 },
 {
  "letter_num":72,
  "from":"Amina Ibrahim",
  "to":"Umar Siraj",
  "date":"9\/11\/17**",
  "location":"Abuja",
  "notes":"sent on the 14th"
 },
 {
  "letter_num":73,
  "from":"Zainab Ibrahim",
  "to":"Rukayya Ibrahim",
  "date":"9\/14\/17**",
  "location":"Katsina",
  "notes":"sent on the 14th in same letter as above"
 },
 {
  "letter_num":74,
  "from":"Usman",
  "to":"Jamila Ibrahim",
  "date":"9\/15\/17**",
  "location":"Borno",
  "notes":null
 },
 {
  "letter_num":75,
  "from":"Fatima, Ibrahim",
  "to":"Muhammad Ibrahim ",
  "date":"9\/14\/17**",
  "location":"Saudia",
  "notes":null
 },
 {
  "letter_num":76,
  "from":"Zainab Ibrahim",
  "to":"Amina Ibrahim",
  "date":"9\/17\/17**",
  "location":"Taraba",
  "notes":null
 },
 {
  "letter_num":77,
  "from":"Muhammad Ibrahim ",
  "to":"Usman",
  "date":"9\/15\/17**",
  "location":"Kano",
  "notes":null
 },
 {
  "letter_num":78,
  "from":"Ibrahim Isah",
  "to":"Fatima, Ibrahim",
  "date":"9\/16\/17**",
  "location":"Adamawa",
  "notes":null
 },
 {
  "letter_num":79,
  "from":"Usman",
  "to":"Fatima, Ibrahim",
  "date":"9\/18\/17**",
  "location":"Abuja",
  "notes":null
 },
 {
  "letter_num":80,
  "from":"Mahmud Musa",
  "to":"Ibrahim Isah",
  "date":"9\/18\/17**",
  "location":"Lagos",
  "notes":null
 },
 {
  "letter_num":81,
  "from":"Maryam Ibrahim",
  "to":"Umar Siraj",
  "date":"9\/20\/17**",
  "location":"Yobe",
  "notes":"Vaincre ou perir"
 },
 {
  "letter_num":82,
  "from":"Rukayya Ibrahim",
  "to":"Jamila Ibrahim",
  "date":"9\/21\/17**",
  "location":"Kano",
  "notes":null
 },
 {
  "letter_num":83,
  "from":"Umar Siraj",
  "to":"Muhammad Ibrahim ",
  "date":"9\/23\/17**",
  "location":"Sokoto",
  "notes":null
 },
 {
  "letter_num":84,
  "from":"Amina Ibrahim",
  "to":"Zainab Ibrahim",
  "date":"9\/24\/17**",
  "location":"Saudia",
  "notes":null
 },
 {
  "letter_num":85,
  "from":"Aisha Sani",
  "to":"Aisha Sani",
  "date":"9\/25\/17**",
  "location":"Kebbi",
  "notes":"au soir"
 },
 {
  "letter_num":86,
  "from":"Jamila Ibrahim",
  "to":"Usman",
  "date":"9\/25\/17**",
  "location":"Katsina",
  "notes":"letter included in previous"
 },
 {
  "letter_num":87,
  "from":"Yusif Kabir",
  "to":"Sani Abdullahi",
  "date":"9\/26\/17**",
  "location":"Borno",
  "notes":null
 },
 {
  "letter_num":88,
  "from":"Sani Abdullahi",
  "to":"Amina Ibrahim",
  "date":"9\/26\/17**",
  "location":"Taraba",
  "notes":null
 },
 {
  "letter_num":89,
  "from":"Nura Abdullahi",
  "to":"Rukayya Ibrahim",
  "date":"9\/26\/17**",
  "location":"USA",
  "notes":null
 },
 {
  "letter_num":90,
  "from":"Ibrahim Isah",
  "to":"Nura Abdullahi",
  "date":"9\/27\/17**",
  "location":"China",
  "notes":null
 },
 {
  "letter_num":91,
  "from":"Amina Ibrahim",
  "to":"Yusif Kabir",
  "date":"9\/27\/17**",
  "location":"Adamawa",
  "notes":null
 },
 {
  "letter_num":92,
  "from":"Usman",
  "to":"Mahmud Musa",
  "date":"9\/27\/17**",
  "location":"China",
  "notes":null
 },
 {
  "letter_num":93,
  "from":"Jamila Ibrahim",
  "to":"Maryam Ibrahim",
  "date":"9\/27\/17**",
  "location":"Yobe",
  "notes":"attached to preceding letter"
 },
 {
  "letter_num":94,
  "from":"Sani Abdullahi",
  "to":"Yusif Kabir",
  "date":"9\/28\/17**",
  "location":"Saudia",
  "notes":null
 },
 {
  "letter_num":95,
  "from":"Fatima, Ibrahim",
  "to":"Fatima, Ibrahim",
  "date":"9\/28\/17**",
  "location":"Taraba",
  "notes":null
 },
 {
  "letter_num":96,
  "from":"Muhammad Ibrahim ",
  "to":"Amina Ibrahim",
  "date":"10\/1\/17**",
  "location":"Kano",
  "notes":null
 },
 {
  "letter_num":97,
  "from":"Nura Abdullahi",
  "to":"Jamila Ibrahim",
  "date":"10\/1\/17**",
  "location":"Sokoto",
  "notes":"seduction of cecile"
 },
 {
  "letter_num":98,
  "from":"Rukayya Ibrahim",
  "to":"Umar Siraj",
  "date":"10\/2\/17**",
  "location":"USA",
  "notes":null
 },
 {
  "letter_num":99,
  "from":"Yusif Kabir",
  "to":"Usman",
  "date":"10\/2\/17**",
  "location":"Borno",
  "notes":"au soir"
 },
 {
  "letter_num":100,
  "from":"Maryam Ibrahim",
  "to":"Rukayya Ibrahim",
  "date":"10\/3\/17**",
  "location":"Abuja",
  "notes":null
 },
 {
  "letter_num":101,
  "from":"Umar Siraj",
  "to":"Muhammad Ibrahim ",
  "date":"10\/3\/17**",
  "location":"Kebbi",
  "notes":"attached to preceding letter"
 },
 {
  "letter_num":102,
  "from":"Aisha Sani",
  "to":"Nura Abdullahi",
  "date":"10\/3\/17**",
  "location":"Lagos",
  "notes":"1h in the morning - departure of Tourvel"
 },
 {
  "letter_num":103,
  "from":"Zainab Ibrahim",
  "to":"Ibrahim Isah",
  "date":"10\/3\/17**",
  "location":"Katsina",
  "notes":null
 },
 {
  "letter_num":104,
  "from":"Mahmud Musa",
  "to":"Maryam Ibrahim",
  "date":"10\/4\/17**",
  "location":"Abuja",
  "notes":null
 },
 {
  "letter_num":105,
  "from":"Sani Abdullahi",
  "to":"Aisha Sani",
  "date":"10\/4\/17**",
  "location":"Borno",
  "notes":null
 },
 {
  "letter_num":106,
  "from":"Umar Siraj",
  "to":"Sani Abdullahi",
  "date":"10\/4\/17**",
  "location":"Taraba",
  "notes":null
 },
 {
  "letter_num":107,
  "from":"Muhammad Ibrahim ",
  "to":"Mahmud Musa",
  "date":"10\/5\/17**",
  "location":"Kano",
  "notes":"11h pm"
 },
 {
  "letter_num":108,
  "from":"Fatima, Ibrahim",
  "to":"Zainab Ibrahim",
  "date":"10\/5\/17**",
  "location":"Lagos",
  "notes":null
 },
 {
  "letter_num":109,
  "from":"Yusif Kabir",
  "to":"Umar Siraj",
  "date":"10\/10\/17**",
  "location":"Saudia",
  "notes":null
 },
 {
  "letter_num":110,
  "from":"Nura Abdullahi",
  "to":"Jamila Ibrahim",
  "date":"10\/11\/17**",
  "location":"China",
  "notes":null
 },
 {
  "letter_num":111,
  "from":"Aisha Sani",
  "to":"Maryam Ibrahim",
  "date":"10\/10\/17**",
  "location":"Adamawa",
  "notes":null
 },
 {
  "letter_num":112,
  "from":"Amina Ibrahim",
  "to":"Rukayya Ibrahim",
  "date":"10\/14\/17**",
  "location":"Yobe",
  "notes":"dictated, signed Adelaide"
 },
 {
  "letter_num":113,
  "from":"Jamila Ibrahim",
  "to":"Usman",
  "date":"10\/15\/17**",
  "location":"USA",
  "notes":null
 },
 {
  "letter_num":114,
  "from":"Rukayya Ibrahim",
  "to":"Zainab Ibrahim",
  "date":"10\/16\/17**",
  "location":"Sokoto",
  "notes":null
 },
 {
  "letter_num":115,
  "from":"Zainab Ibrahim",
  "to":"Ibrahim Isah",
  "date":"10\/19\/17**",
  "location":"Katsina",
  "notes":null
 },
 {
  "letter_num":116,
  "from":"Mahmud Musa",
  "to":"Mahmud Musa",
  "date":"10\/17\/17**",
  "location":"Kebbi",
  "notes":null
 },
 {
  "letter_num":117,
  "from":"Ibrahim Isah",
  "to":"Amina Ibrahim",
  "date":"10\/18\/17**",
  "location":"Katsina",
  "notes":"dictated by Valmont"
 },
 {
  "letter_num":118,
  "from":"Maryam Ibrahim",
  "to":"Aisha Sani",
  "date":"10\/19\/17**",
  "location":"Borno",
  "notes":null
 },
 {
  "letter_num":119,
  "from":"Usman",
  "to":"Muhammad Ibrahim ",
  "date":"10\/20\/17**",
  "location":"Taraba",
  "notes":null
 },
 {
  "letter_num":120,
  "from":"Muhammad Ibrahim ",
  "to":"Nura Abdullahi",
  "date":"10\/22\/17**",
  "location":"Adamawa",
  "notes":null
 },
 {
  "letter_num":121,
  "from":"Nura Abdullahi",
  "to":"Sani Abdullahi",
  "date":"10\/22\/17**",
  "location":"Saudia",
  "notes":null
 },
 {
  "letter_num":122,
  "from":"Ibrahim Isah",
  "to":"Yusif Kabir",
  "date":"10\/25\/17**",
  "location":"Abuja",
  "notes":null
 },
 {
  "letter_num":123,
  "from":"Jamila Ibrahim",
  "to":"Fatima, Ibrahim",
  "date":"10\/25\/17**",
  "location":"USA",
  "notes":null
 },
 {
  "letter_num":124,
  "from":"Aisha Sani",
  "to":"Sani Abdullahi",
  "date":"10\/25\/17**",
  "location":"Lagos",
  "notes":null
 },
 {
  "letter_num":125,
  "from":"Zainab Ibrahim",
  "to":"Maryam Ibrahim",
  "date":"10\/29\/17**",
  "location":"Kebbi",
  "notes":"success of Valmont w\/ Tourvel"
 },
 {
  "letter_num":126,
  "from":"Fatima, Ibrahim",
  "to":"Mahmud Musa",
  "date":"10\/30\/17**",
  "location":"Yobe",
  "notes":null
 },
 {
  "letter_num":127,
  "from":"Mahmud Musa",
  "to":"Yusif Kabir",
  "date":"10\/31\/17**",
  "location":"Kano",
  "notes":null
 },
 {
  "letter_num":128,
  "from":"Maryam Ibrahim",
  "to":"Muhammad Ibrahim ",
  "date":"11\/1\/17**",
  "location":"China",
  "notes":null
 },
 {
  "letter_num":129,
  "from":"Yusif Kabir",
  "to":"Jamila Ibrahim",
  "date":"11\/3\/17**",
  "location":"Sokoto",
  "notes":null
 },
 {
  "letter_num":130,
  "from":"Rukayya Ibrahim",
  "to":"Umar Siraj",
  "date":"11\/4\/17**",
  "location":"Adamawa",
  "notes":null
 },
 {
  "letter_num":131,
  "from":"Amina Ibrahim",
  "to":"Amina Ibrahim",
  "date":"11\/6\/17**",
  "location":"China",
  "notes":null
 },
 {
  "letter_num":132,
  "from":"Sani Abdullahi",
  "to":"Ibrahim Isah",
  "date":"11\/7\/17**",
  "location":"Borno",
  "notes":null
 },
 {
  "letter_num":133,
  "from":"Umar Siraj",
  "to":"Aisha Sani",
  "date":"11\/8\/17**",
  "location":"Sokoto",
  "notes":null
 },
 {
  "letter_num":134,
  "from":"Usman",
  "to":"Nura Abdullahi",
  "date":"11\/11\/17*",
  "location":"Abuja",
  "notes":null
 },
 {
  "letter_num":135,
  "from":"Nura Abdullahi",
  "to":"Fatima, Ibrahim",
  "date":"11\/15\/17**",
  "location":"Saudia",
  "notes":"valmont w\/ prostitute"
 },
 {
  "letter_num":136,
  "from":"Amina Ibrahim",
  "to":"Usman",
  "date":"11\/15\/17**",
  "location":"USA",
  "notes":null
 },
 {
  "letter_num":137,
  "from":"Usman",
  "to":"Zainab Ibrahim",
  "date":"11\/15\/17**",
  "location":"Lagos",
  "notes":null
 },
 {
  "letter_num":138,
  "from":"Yusif Kabir",
  "to":"Rukayya Ibrahim",
  "date":"11\/15\/17**",
  "location":"Yobe",
  "notes":null
 },
 {
  "letter_num":139,
  "from":"Ibrahim Isah",
  "to":"Nura Abdullahi",
  "date":"11\/16\/17**",
  "location":"Katsina",
  "notes":"au soir"
 },
 {
  "letter_num":140,
  "from":"Mahmud Musa",
  "to":"Mahmud Musa",
  "date":"11\/21\/17**",
  "location":"Kano",
  "notes":null
 },
 {
  "letter_num":141,
  "from":"Maryam Ibrahim",
  "to":"Fatima, Ibrahim",
  "date":"11\/24\/17**",
  "location":"Kebbi",
  "notes":null
 },
 {
  "letter_num":142,
  "from":"Jamila Ibrahim",
  "to":"Yusif Kabir",
  "date":"11\/27\/17**",
  "location":"Taraba",
  "notes":null
 },
 {
  "letter_num":143,
  "from":"Muhammad Ibrahim ",
  "to":"Maryam Ibrahim",
  "date":"11\/27\/17**",
  "location":"China",
  "notes":null
 },
 {
  "letter_num":144,
  "from":"Zainab Ibrahim",
  "to":"Muhammad Ibrahim ",
  "date":"11\/28\/17**",
  "location":"Katsina",
  "notes":null
 },
 {
  "letter_num":145,
  "from":"Sani Abdullahi",
  "to":"Aisha Sani",
  "date":"11\/29\/17**",
  "location":"Adamawa",
  "notes":null
 },
 {
  "letter_num":146,
  "from":"Rukayya Ibrahim",
  "to":"Usman",
  "date":"11\/29\/17**",
  "location":"Taraba",
  "notes":null
 },
 {
  "letter_num":147,
  "from":"Aisha Sani",
  "to":"Umar Siraj",
  "date":"11\/29\/17**",
  "location":"Lagos",
  "notes":null
 },
 {
  "letter_num":148,
  "from":"Fatima, Ibrahim",
  "to":"Ibrahim Isah",
  "date":"12\/1\/17**",
  "location":"Abuja",
  "notes":null
 },
 {
  "letter_num":149,
  "from":"Umar Siraj",
  "to":"Rukayya Ibrahim",
  "date":"12\/2\/17**",
  "location":"Saudia",
  "notes":null
 },
 {
  "letter_num":150,
  "from":"Ibrahim Isah",
  "to":"Jamila Ibrahim",
  "date":"12\/3\/17**",
  "location":"Kebbi",
  "notes":null
 },
 {
  "letter_num":151,
  "from":"Rukayya Ibrahim",
  "to":"Amina Ibrahim",
  "date":"12\/3\/17**",
  "location":"Borno",
  "notes":null
 },
 {
  "letter_num":152,
  "from":"Aisha Sani",
  "to":"Sani Abdullahi",
  "date":"12\/4\/17**",
  "location":"USA",
  "notes":null
 },
 {
  "letter_num":153,
  "from":"Usman",
  "to":"Zainab Ibrahim",
  "date":"12\/4\/17**",
  "location":"Kano",
  "notes":"at the bottom, mme de M write 'eh bien, la guerre'"
 },
 {
  "letter_num":154,
  "from":"Fatima, Ibrahim",
  "to":"Mahmud Musa",
  "date":"12\/5\/17**",
  "location":"Sokoto",
  "notes":null
 },
 {
  "letter_num":155,
  "from":"Sani Abdullahi",
  "to":"Umar Siraj",
  "date":"12\/5\/17**",
  "location":"Yobe",
  "notes":null
 },
 {
  "letter_num":156,
  "from":"Amina Ibrahim",
  "to":"Ibrahim Isah",
  "date":"12\/4\/17**",
  "location":"Yobe",
  "notes":null
 },
 {
  "letter_num":157,
  "from":"Nura Abdullahi",
  "to":"Nura Abdullahi",
  "date":"12\/5\/17**",
  "location":"Taraba",
  "notes":null
 },
 {
  "letter_num":158,
  "from":"Umar Siraj",
  "to":"Aisha Sani",
  "date":"12\/6\/17**",
  "location":"Saudia",
  "notes":null
 },
 {
  "letter_num":159,
  "from":"Maryam Ibrahim",
  "to":"Fatima, Ibrahim",
  "date":"12\/6\/17**",
  "location":"Borno",
  "notes":null
 },
 {
  "letter_num":160,
  "from":"Mahmud Musa",
  "to":"Yusif Kabir",
  "date":"12\/6\/17**",
  "location":"Lagos",
  "notes":null
 },
 {
  "letter_num":161,
  "from":"Yusif Kabir",
  "to":"Amina Ibrahim",
  "date":"12\/5\/17**",
  "location":"USA",
  "notes":"dictated to her maid"
 },
 {
  "letter_num":162,
  "from":"Muhammad Ibrahim ",
  "to":"Rukayya Ibrahim",
  "date":"12\/6\/17**",
  "location":"Sokoto",
  "notes":"duel challenge"
 },
 {
  "letter_num":163,
  "from":"Zainab Ibrahim",
  "to":"Usman",
  "date":"12\/7\/17**",
  "location":"Abuja",
  "notes":"death of Valmont"
 },
 {
  "letter_num":164,
  "from":"Jamila Ibrahim",
  "to":"Zainab Ibrahim",
  "date":"12\/8\/17**",
  "location":"Adamawa",
  "notes":null
 },
 {
  "letter_num":165,
  "from":"Mahmud Musa",
  "to":"Sani Abdullahi",
  "date":"12\/9\/17**",
  "location":"Kano",
  "notes":"death of Presidente"
 },
 {
  "letter_num":166,
  "from":"Ibrahim Isah",
  "to":"Maryam Ibrahim",
  "date":"12\/10\/17**",
  "location":"Kebbi",
  "notes":null
 },
 {
  "letter_num":167,
  "from":"Yusif Kabir",
  "to":"Muhammad Ibrahim ",
  "date":"12\/10\/17**",
  "location":"Katsina",
  "notes":null
 },
 {
  "letter_num":168,
  "from":"Aisha Sani",
  "to":"Jamila Ibrahim",
  "date":"12\/11\/17**",
  "location":"China",
  "notes":null
 },
 {
  "letter_num":169,
  "from":"Umar Siraj",
  "to":"Mahmud Musa",
  "date":"12\/12\/17**",
  "location":"Kano",
  "notes":"revelation of letters"
 },
 {
  "letter_num":170,
  "from":"Rukayya Ibrahim",
  "to":"Jamila Ibrahim",
  "date":"12\/13\/17**",
  "location":"Yobe",
  "notes":"plan to send cecile back to convent"
 },
 {
  "letter_num":171,
  "from":"Usman",
  "to":"Maryam Ibrahim",
  "date":"12\/13\/17**",
  "location":"Kebbi",
  "notes":"drop charges"
 },
 {
  "letter_num":172,
  "from":"Amina Ibrahim",
  "to":"Yusif Kabir",
  "date":"12\/15\/17**",
  "location":"China",
  "notes":null
 },
 {
  "letter_num":173,
  "from":"Jamila Ibrahim",
  "to":"Muhammad Ibrahim ",
  "date":"12\/18\/17**",
  "location":"Saudia",
  "notes":"booing, fever of Merteuil"
 },
 {
  "letter_num":174,
  "from":"Muhammad Ibrahim ",
  "to":"Amina Ibrahim",
  "date":"12\/26\/17**",
  "location":"Adamawa",
  "notes":null
 },
 {
  "letter_num":175,
  "from":"Sani Abdullahi",
  "to":"Rukayya Ibrahim",
  "date":"1\/14\/17**",
  "location":"USA",
  "notes":"downfall of Merteuil"
 }
]